dtwheel/__init__.py
dtwheel/_helpers.py
dtwheel/_version.py
dtwheel/checks.py
dtwheel/constants.py
dtwheel/deltas.py
dtwheel/formatters.py
dtwheel/parsers.py
dtwheel/relative.py
dtwheel/timezone.py
dtwheel-0.1.0.dist-info/LICENSE
dtwheel-0.1.0.dist-info/METADATA
dtwheel-0.1.0.dist-info/WHEEL
dtwheel-0.1.0.dist-info/RECORD
