Metadata-Version: 2.3
Name: dtwheel
Version: 0.1.0
Summary: Intuitive Datetime Manipulation for Python
License: MIT
Keywords: datetime,date,time,utility,timezones
Author: Your Name
Author-email: ucsa8005@gmail.com
Requires-Python: >=3.9,<4.0
Classifier: Development Status :: 3 - Alpha
Classifier: Intended Audience :: Developers
Classifier: License :: OSI Approved :: MIT License
Classifier: Operating System :: OS Independent
Classifier: Programming Language :: Python :: 3
Classifier: Programming Language :: Python :: 3.9
Classifier: Programming Language :: Python :: 3.10
Classifier: Programming Language :: Python :: 3.11
Classifier: Programming Language :: Python :: 3.12
Classifier: Programming Language :: Python :: 3.13
Classifier: Topic :: Software Development :: Libraries :: Python Modules
Requires-Dist: tzdata (>=2024.1,<2025.0)
Project-URL: Homepage, https://github.com/UdhayChandra/dtwheel
Project-URL: Repository, https://github.com/UdhayChandra/dtwheel
